bprint.py
beauty_print-0.6.0.dist-info/LICENSE.txt
beauty_print-0.6.0.dist-info/METADATA
beauty_print-0.6.0.dist-info/WHEEL
beauty_print-0.6.0.dist-info/top_level.txt
beauty_print-0.6.0.dist-info/RECORD
