Metadata-Version: 2.1
Name: beauty-print
Version: 0.6.0
Summary: Beautifully print Python data
Home-page: https://github.com/Lonami/bprint
Author: Lonami
Author-email: totufals@hotmail.com
License: CC0
Download-URL: https://github.com/Lonami/bprint
Keywords: print pprint
Platform: UNKNOWN
Classifier: Development Status :: 5 - Production/Stable
Classifier: Intended Audience :: Developers
Classifier: Topic :: Communications :: Chat
Classifier: License :: OSI Approved :: MIT License
Classifier: Programming Language :: Python :: 3
Classifier: Programming Language :: Python :: 3.6
Classifier: Programming Language :: Python :: 3.7
Requires-Python: >=3.6
